{
  "kind": "collectionType",
  "collectionName": "reviews",
  "info": {
    "singularName": "review",
    "pluralName": "reviews",
    "displayName": "Review"
  },
  "options": {
    "draftAndPublish": true
  },
  "attributes": {
    "title": {
      "type": "string",
      "required": true
    },
    "text": {
      "type": "richtext",
      "required": true
    },
    "rating": {
      "type": "integer"
    },
    "users_permissions_user": {
      "type": "relation",
      "relation": "manyToOne",
      "target": "plugin::users-permissions.user",
      "inversedBy": "reviews"
    },
    "likes": {
      "type": "relation",
      "relation": "manyToMany",
      "target": "plugin::users-permissions.user",
      "inversedBy": "users"
    }
  }
}
